autoklik/__init__.py
autoklik/__main__.py
autoklik/main.py
autoklik-0.2.0.dist-info/LICENSE
autoklik-0.2.0.dist-info/METADATA
autoklik-0.2.0.dist-info/WHEEL
autoklik-0.2.0.dist-info/entry_points.txt
autoklik-0.2.0.dist-info/RECORD
