Metadata-Version: 2.1
Name: autoklik
Version: 0.2.0
Summary: Auto clicker built around xdotool.
Home-page: https://git.walbeck.it/mwalbeck/autoklik
Author: Magnus Walbeck
Author-email: mw@mwalbeck.org
Requires-Python: >=3.8,<4.0
Classifier: Programming Language :: Python :: 3
Classifier: Programming Language :: Python :: 3.8
Classifier: Programming Language :: Python :: 3.9
Classifier: Programming Language :: Python :: 3.10
Classifier: Programming Language :: Python :: 3.11
Project-URL: Repository, https://git.walbeck.it/mwalbeck/autoklik
